README.rst
setup.py
stackexchangepy/__init__.py
stackexchangepy/client.py
stackexchangepy/exception.py
stackexchangepy/helpers.py
stackexchangepy/model.py
stackexchangepy/oauth2.py
stackexchangepy/request.py
stackexchangepy/sites.py
stackexchangepy.egg-info/PKG-INFO
stackexchangepy.egg-info/SOURCES.txt
stackexchangepy.egg-info/dependency_links.txt
stackexchangepy.egg-info/requires.txt
stackexchangepy.egg-info/top_level.txt
stackexchangepy/module/__init__.py
stackexchangepy/module/answer.py
stackexchangepy/module/badge.py
stackexchangepy/module/comment.py
stackexchangepy/module/event.py
stackexchangepy/module/info.py
stackexchangepy/module/me.py
stackexchangepy/module/post.py
stackexchangepy/module/privilege.py
stackexchangepy/module/question.py
stackexchangepy/module/revision.py
stackexchangepy/module/search.py
stackexchangepy/module/suggested_edit.py
stackexchangepy/module/tag.py
stackexchangepy/module/user.py
stackexchangepy/network/__init__.py
stackexchangepy/network/access_token.py
stackexchangepy/network/app.py
stackexchangepy/network/error.py
stackexchangepy/network/filter.py
stackexchangepy/network/inbox.py
stackexchangepy/network/me.py
stackexchangepy/network/network.py
stackexchangepy/network/notification.py
stackexchangepy/network/site.py
stackexchangepy/network/user.py