Metadata-Version: 1.1
Name: stackexchangepy
Version: 1.0.0
Summary: StackExchangePy API Wrapper
Home-page: https://github.com/monzita/stackexchangepy
Author: Monika Ilieva
Author-email: hidden@hidden.com
License: GNU General Public License v3 or later (GPLv3+)
Keywords: stackexchangepy api wrapper python3
Platform: UNKNOWN
Classifier: Development Status :: 3 - Alpha
Classifier: Intended Audience :: Developers
Classifier: Topic :: Software Development :: Build Tools
Classifier: License :: OSI Approved :: GNU General Public License v3 or later (GPLv3+)
Classifier: Programming Language :: Python :: 3.6
